{
    "id": "entrepreneurship",
    "title": "Entrepreneurship",
    "category": "Management & Entrepreneurship",

    "link": "https://app.schoolinks.com/student-pathways/entrepreneurship/",
    "tcd": false,

    "requirements": {
        "pathwayType": "Regular",
        "courseCredits": {
        "totalCreditsRequired": 2.5,

        "requiredCourses": [
            {
            "name": "Business INCubatoredu",
            "credits": 1.0,
            "earlyCollegeCredit": true 
            },
            {
            "name": "Blended Business ACCELeratoredu",
            "credits": 1.0,
            "earlyCollegeCredit": false 
            }
        ],

        "electiveCreditsRequired": 0.5,

        "electiveCourseOptions": [
            {
                "name": "Accounting 1",
                "credits": 1.0,
                "earlyCollegeCredit": true
            },
            {
                "name": "Marketing",
                "credits": 0.5,
                "earlyCollegeCredit": true
            },
            {
                "name": "AP Macroeconomics",
                "credits": 0.5,
                "earlyCollegeCredit": true
            },
            {
                "name": "AP Microeconomics",
                "credits": 0.5,
                "earlyCollegeCredit": true
            }
        ]
    },
    "professionalLearning": {
      "notes": "these hours are embedded within the required career-focused coursework",
      "careerExplorationActivities": 2,
      "teamChallenges": 2,
      "workExperienceHours": 60
    }
  },
  "imageFile": "entreprenuership.jpg",
  "imagePath": "/endorsements/images/entreprenuership.jpg"
}
